slogging/__init__.py
slogging/access_log_delivery.py
slogging/access_processor.py
slogging/common.py
slogging/compressing_file_reader.py
slogging/db_stats_collector.py
slogging/file_buffer.py
slogging/internal_proxy.py
slogging/log_common.py
slogging/log_processor.py
slogging/log_uploader.py
slogging/stats_processor.py
slogging-1.2.1.data/data/etc/access-log-delivery.conf-sample
slogging-1.2.1.data/data/etc/log-processor.conf-sample
slogging-1.2.1.data/scripts/swift-access-log-delivery
slogging-1.2.1.data/scripts/swift-account-stats-logger
slogging-1.2.1.data/scripts/swift-container-stats-logger
slogging-1.2.1.data/scripts/swift-log-stats-collector
slogging-1.2.1.data/scripts/swift-log-uploader
slogging-1.2.1.dist-info/METADATA
slogging-1.2.1.dist-info/RECORD
slogging-1.2.1.dist-info/WHEEL
slogging-1.2.1.dist-info/pbr.json
slogging-1.2.1.dist-info/top_level.txt
